LICENSE
MANIFEST.in
README.md
requirements.txt
setup.py
autoBOTLib/__init__.py
autoBOTLib/__main__.py
autoBOTLib.egg-info/PKG-INFO
autoBOTLib.egg-info/SOURCES.txt
autoBOTLib.egg-info/dependency_links.txt
autoBOTLib.egg-info/entry_points.txt
autoBOTLib.egg-info/not-zip-safe
autoBOTLib.egg-info/requires.txt
autoBOTLib.egg-info/top_level.txt
autoBOTLib/features/__init__.py
autoBOTLib/features/features_concepts.py
autoBOTLib/features/features_contextual.py
autoBOTLib/features/features_document_graph.py
autoBOTLib/features/features_images.py
autoBOTLib/features/features_keyword.py
autoBOTLib/features/features_sentence_embeddings.py
autoBOTLib/features/features_token_relations.py
autoBOTLib/features/features_topic.py
autoBOTLib/learning/__init__.py
autoBOTLib/learning/hyperparameter_configurations.py
autoBOTLib/learning/scikit_based.py
autoBOTLib/learning/torch_sparse_nn.py
autoBOTLib/misc/__init__.py
autoBOTLib/misc/misc_helpers.py
autoBOTLib/misc/misc_keyword_detection.py
autoBOTLib/optimization/__init__.py
autoBOTLib/optimization/optimization_engine.py
autoBOTLib/optimization/optimization_feature_constructors.py
autoBOTLib/optimization/optimization_metrics.py
autoBOTLib/optimization/optimization_random.py
autoBOTLib/optimization/optimization_utils.py