Metadata-Version: 2.1
Name: autoBOTLib
Version: 1.19
Summary: AutoBOT: Explainable AutoML for texts
Home-page: https://github.com/skblaz/autobot
Author: Blaž Škrlj
Author-email: blaz.skrlj@ijs.si
License: bsd-3-clause-clear
Platform: UNKNOWN
License-File: LICENSE
